docker_compose_wait.py
timeparse.py
docker_compose_wait_cksource-1.3.0.dist-info/LICENSE.md
docker_compose_wait_cksource-1.3.0.dist-info/METADATA
docker_compose_wait_cksource-1.3.0.dist-info/WHEEL
docker_compose_wait_cksource-1.3.0.dist-info/entry_points.txt
docker_compose_wait_cksource-1.3.0.dist-info/top_level.txt
docker_compose_wait_cksource-1.3.0.dist-info/RECORD
