Metadata-Version: 2.1
Name: docker-compose-wait-cksource
Version: 1.3.0
Summary: Some useful command line utility to wait until all services declared in a docker-compose file are up and running.
Home-page: https://github.com/nicolas-van/docker-compose-wait
Author: Nicolas Vanhoren
License: UNKNOWN
Project-URL: Bug Reports, https://github.com/nicolas-van/docker-compose-wait/issues
Project-URL: Source, https://github.com/nicolas-van/docker-compose-wait
Keywords: docker container util
Platform: UNKNOWN
Classifier: Development Status :: 4 - Beta
Classifier: Environment :: Console
Classifier: Intended Audience :: System Administrators
Classifier: Operating System :: OS Independent
Classifier: Topic :: System :: Systems Administration
Classifier: License :: OSI Approved :: MIT License
Classifier: Programming Language :: Python :: 2
Classifier: Programming Language :: Python :: 2.7
Classifier: Programming Language :: Python :: 3
Classifier: Programming Language :: Python :: 3.3
Classifier: Programming Language :: Python :: 3.4
Classifier: Programming Language :: Python :: 3.5
Classifier: Programming Language :: Python :: 3.6
Requires-Python: >=2.7,!=3.0.*,!=3.1.*,!=3.2.*
Requires-Dist: PyYAML (>=3.12)
